rmtest/__init__.py
rmtest/cluster.py
rmtest/disposableredis/__init__.py
rmtest/disposableredis/cluster.py
rmtest-0.6.9.dist-info/METADATA
rmtest-0.6.9.dist-info/RECORD
rmtest-0.6.9.dist-info/WHEEL
rmtest-0.6.9.dist-info/top_level.txt
