Metadata-Version: 2.1
Name: rmtest
Version: 0.6.9
Summary: Redis Module Testing Utility
Home-page: http://github.com/RedisLabs/rmtest
Author: UNKNOWN
Author-email: UNKNOWN
License: UNKNOWN
Platform: UNKNOWN
Classifier: Development Status :: 4 - Beta
Classifier: Intended Audience :: Developers
Classifier: License :: OSI Approved :: BSD License
Classifier: Programming Language :: Python :: 2.7
Classifier: Topic :: Database
Classifier: Topic :: Software Development :: Testing
Requires-Dist: redis
